gh_copilot_chat/__init__.py
gh_copilot_chat/constants.py
gh_copilot_chat/copilot.py
gh_copilot_chat/main.py
gh_copilot_chat-2024.5.11.505.dist-info/METADATA
gh_copilot_chat-2024.5.11.505.dist-info/WHEEL
gh_copilot_chat-2024.5.11.505.dist-info/entry_points.txt
gh_copilot_chat-2024.5.11.505.dist-info/RECORD
