Metadata-Version: 2.1
Name: gh_copilot_chat
Version: 2024.5.11.505
Summary: API Wrapper for GitHub Copilot Chat
Author: Mohammed Rabil
Author-email: rabil@email.com
Requires-Python: >=3.11,<4.0
Classifier: Programming Language :: Python :: 3
Classifier: Programming Language :: Python :: 3.11
Classifier: Programming Language :: Python :: 3.12
Requires-Dist: aiohttp (>=3.9.5,<4.0.0)
Requires-Dist: python-dotenv (>=1.0.1,<2.0.0)
